errors/non_overridable_error.py
errors/test_failure.py
pyster/__init__.py
pyster/endreport.py
pyster/options.py
pyster/pyster.py
pyster/pysterminal.py
python_pyster-0.1.17.dist-info/LICENSE.txt
python_pyster-0.1.17.dist-info/METADATA
python_pyster-0.1.17.dist-info/WHEEL
python_pyster-0.1.17.dist-info/entry_points.txt
python_pyster-0.1.17.dist-info/top_level.txt
python_pyster-0.1.17.dist-info/RECORD
